nose_warnings_filters/__init__.py
nose_warnings_filters/base.py
nose_warnings_filters/testing/__init__.py
nose_warnings_filters/testing/test_config.py
nose_warnings_filters/testing/utils.py
nose_warnings_filters-0.1.5.dist-info/DESCRIPTION.rst
nose_warnings_filters-0.1.5.dist-info/METADATA
nose_warnings_filters-0.1.5.dist-info/RECORD
nose_warnings_filters-0.1.5.dist-info/WHEEL
nose_warnings_filters-0.1.5.dist-info/entry_points.txt
nose_warnings_filters-0.1.5.dist-info/metadata.json
nose_warnings_filters-0.1.5.dist-info/pbr.json
nose_warnings_filters-0.1.5.dist-info/top_level.txt
