Metadata-Version: 2.0
Name: nose-warnings-filters
Version: 0.1.5
Summary: Allow to inject warning filters during ``nosetest``.
Requires-Dist: nose
